jibit/__init__.py
jibit/exceptions.py
jibit/helpers.py
jibit/jibit_service.py
jibit/models.py
jibit-1.2.4.dist-info/METADATA
jibit-1.2.4.dist-info/WHEEL
jibit-1.2.4.dist-info/RECORD
