Metadata-Version: 2.1
Name: jibit
Version: 1.2.4
Summary: python tool for jbit.ir apis
Home-page: https://github.com/s7eed/jibit
License: MIT
Author: s7eed
Author-email: s7eed.b@gmail.com
Requires-Python: >=3.9,<4.0
Classifier: License :: OSI Approved :: MIT License
Classifier: Programming Language :: Python :: 3
Classifier: Programming Language :: Python :: 3.9
Classifier: Programming Language :: Python :: 3.10
Classifier: Programming Language :: Python :: 3.11
Classifier: Programming Language :: Python :: 3.12
Requires-Dist: aiohttp (>=3.8,<4.0)
Project-URL: Documentation, https://github.com/s7eed/jibit#readme
Project-URL: Repository, https://github.com/s7eed/jibit
